<?xml version="1.0" encoding="UTF-8"?><database>
    <element db_object_id="655d65002fa48a10c9a958a72799b626" label="License Activity" max_length="40" name="x_880490_2s_licens_license_activity" type="collection">
        <element label="Days since last activity" max_length="40" name="days_since_last_activity" type="integer"/>
        <element attributes="edge_encryption_enabled=true" label="Last activity date" max_length="40" name="last_activity_date" type="glide_date"/>
        <element attributes="encode_utf8=false" label="License Name" max_length="32" name="license_name" reference="x_880490_2s_licens_license_definition" type="reference"/>
        <element attributes="edge_encryption_enabled=true" default="javascript:global.getNextObjNumberPadded();" label="Number" max_length="40" name="number" type="string"/>
        <element default="javascript:current.getTableName();" label="Class" max_length="80" name="sys_class_name" type="sys_class_name"/>
        <element attributes="encode_utf8=false" label="User" max_length="32" name="user" reference="sys_user" type="reference"/>
        <index name="index">
            <element name="license_name"/>
        </index>
        <index name="index2">
            <element name="sys_class_name"/>
        </index>
        <index name="index3">
            <element name="user"/>
        </index>
    </element>
</database>
